pnap_payments_api/__init__.py
pnap_payments_api/api_client.py
pnap_payments_api/api_response.py
pnap_payments_api/configuration.py
pnap_payments_api/exceptions.py
pnap_payments_api/py.typed
pnap_payments_api/rest.py
pnap_payments_api/version.py
pnap_payments_api/api/__init__.py
pnap_payments_api/api/transactions_api.py
pnap_payments_api/models/__init__.py
pnap_payments_api/models/card_payment_method_details.py
pnap_payments_api/models/error.py
pnap_payments_api/models/paginated_response.py
pnap_payments_api/models/paginated_transactions.py
pnap_payments_api/models/transaction.py
pnap_payments_api/models/transaction_metadata.py
pnap_payments_api-1.0.4.dist-info/METADATA
pnap_payments_api-1.0.4.dist-info/WHEEL
pnap_payments_api-1.0.4.dist-info/top_level.txt
pnap_payments_api-1.0.4.dist-info/RECORD
