Metadata-Version: 2.1
Name: pnap-payments-api
Version: 1.0.4
Summary: Payments API
Home-page: UNKNOWN
Author: PhoenixNAP Team
Author-email: support@phoenixnap.com
License: Apache 2.0
Keywords: OpenAPI,OpenAPI-Generator,Payments API
Platform: UNKNOWN
Requires-Dist: urllib3 <2.1.0,>=1.25.3
Requires-Dist: python-dateutil
Requires-Dist: pydantic >=2
Requires-Dist: typing-extensions >=4.7.1
